server/__init__.py
server/server.py
server/common/__init__.py
server/common/decos.py
server/common/descryptors.py
server/common/errors.py
server/common/metaclasses.py
server/common/utils.py
server/common/variables.py
server/logs/__init__.py
server/server/__init__.py
server/server/add_user.py
server/server/config_window.py
server/server/core.py
server/server/database.py
server/server/main_window.py
server/server/remove_user.py
server/server/stat_window.py
server/unit_tests/__init__.py
my_proj_mess_server-0.0.1.dist-info/METADATA
my_proj_mess_server-0.0.1.dist-info/WHEEL
my_proj_mess_server-0.0.1.dist-info/top_level.txt
my_proj_mess_server-0.0.1.dist-info/RECORD
